{"devicePlatform":"","logFolder":"C:\\Users\\smanugunta\\git\\Test\\Reports\\TestSuite1\\20180507_140550","runData":{"hostName":"smanugunta - USR-SMANUGUNTA1.avoka.local","os":"Windows 10 64bit","katalonVersion":"5.4.1.1","browser":"Chrome 66.0.3359.139","hostAddress":"192.168.20.233","sessionId":"aaf4ac5331c374c1ce4952bb373b958a","seleniumVersion":"3.7.1","proxyInformation":"ProxyInformation{proxyOption\u003dNO_PROXY, proxyServerType\u003dHTTP, password\u003d, proxyServerAddress\u003d, proxyServerPort\u003d0}","platform":"Windows 10"},"type":"TEST_SUITE","name":"TestSuite1","id":"Test Suites/TestSuite1","source":"","message":"Test Cases/Testcase2","description":"","startTime":1525665951565,"endTime":1525665999749,"childRecords":[{"isOptional":false,"type":"TEST_CASE","name":"Test Cases/Testcase1","id":"Test Cases/Testcase1","source":"C:\\\\Users\\\\smanugunta\\\\git\\\\Test\\\\Test Cases\\\\Testcase1.tc","message":"Test Cases/Testcase1","description":"Manager Login \u0026 Logout","startTime":1525665951876,"endTime":1525665977101,"childRecords":[{"testStatus":{"stackTrace":"","statusValue":"INFO"},"type":"MESSAGE","name":"","message":"Evaluating variables for test case","startTime":1525665951909,"endTime":0,"childRecords":[],"interuppted":false},{"index":1,"isIgnoredIfFailed":false,"type":"TEST_STEP","name":"openBrowser","message":"Browser is opened with url: \u0027\u0027","description":"","startTime":1525665952306,"endTime":1525665955337,"childRecords":[{"testStatus":{"stackTrace":"","statusValue":"PASSED"},"type":"MESSAGE","name":"","message":"Browser is opened with url: \u0027\u0027","startTime":1525665955336,"endTime":0,"childRecords":[],"interuppted":false}],"interuppted":false},{"index":2,"isIgnoredIfFailed":false,"type":"TEST_STEP","name":"navigateToUrl","message":"Navigate to \u0027https://tm.test1.avoka.com/manager/login.htm\u0027 successfully","description":"Open Url\\r\\n","startTime":1525665955338,"endTime":1525665957600,"childRecords":[{"testStatus":{"stackTrace":"","statusValue":"PASSED"},"type":"MESSAGE","name":"","message":"Navigate to \u0027https://tm.test1.avoka.com/manager/login.htm\u0027 successfully","startTime":1525665957599,"endTime":0,"childRecords":[],"interuppted":false}],"interuppted":false},{"index":3,"isIgnoredIfFailed":false,"type":"TEST_STEP","name":"setText","message":"Text \u0027smanugunta@avoka.com\u0027 is set on object \u0027Object Repository/MainPage/input_j_username\u0027","description":"","startTime":1525665957600,"endTime":1525665957854,"childRecords":[{"testStatus":{"stackTrace":"","statusValue":"PASSED"},"type":"MESSAGE","name":"","message":"Text \u0027smanugunta@avoka.com\u0027 is set on object \u0027Object Repository/MainPage/input_j_username\u0027","startTime":1525665957853,"endTime":0,"childRecords":[],"interuppted":false}],"interuppted":false},{"index":4,"isIgnoredIfFailed":false,"type":"TEST_STEP","name":"setText","message":"Text \u0027Unicorn!23\u0027 is set on object \u0027Object Repository/MainPage/input_j_password\u0027","description":"","startTime":1525665957854,"endTime":1525665957972,"childRecords":[{"testStatus":{"stackTrace":"","statusValue":"PASSED"},"type":"MESSAGE","name":"","message":"Text \u0027Unicorn!23\u0027 is set on object \u0027Object Repository/MainPage/input_j_password\u0027","startTime":1525665957971,"endTime":0,"childRecords":[],"interuppted":false}],"interuppted":false},{"index":5,"isIgnoredIfFailed":false,"type":"TEST_STEP","name":"click","message":"Object: \u0027Object Repository/MainPage/input_btn btn-primary\u0027 is clicked on","description":"","startTime":1525665957972,"endTime":1525665961584,"childRecords":[{"testStatus":{"stackTrace":"","statusValue":"PASSED"},"type":"MESSAGE","name":"","message":"Object: \u0027Object Repository/MainPage/input_btn btn-primary\u0027 is clicked on","startTime":1525665961584,"endTime":0,"childRecords":[],"interuppted":false}],"interuppted":false},{"index":6,"isIgnoredIfFailed":false,"type":"TEST_STEP","name":"click","message":"Object: \u0027Object Repository/MainPage/a_Form Spaces\u0027 is clicked on","description":"","startTime":1525665961585,"endTime":1525665963951,"childRecords":[{"testStatus":{"stackTrace":"","statusValue":"PASSED"},"type":"MESSAGE","name":"","message":"Object: \u0027Object Repository/MainPage/a_Form Spaces\u0027 is clicked on","startTime":1525665963950,"endTime":0,"childRecords":[],"interuppted":false}],"interuppted":false},{"index":7,"isIgnoredIfFailed":false,"type":"TEST_STEP","name":"setText","message":"Text \u0027test\u0027 is set on object \u0027Object Repository/MainPage/input_searchField\u0027","description":"","startTime":1525665963951,"endTime":1525665964080,"childRecords":[{"testStatus":{"stackTrace":"","statusValue":"PASSED"},"type":"MESSAGE","name":"","message":"Text \u0027test\u0027 is set on object \u0027Object Repository/MainPage/input_searchField\u0027","startTime":1525665964080,"endTime":0,"childRecords":[],"interuppted":false}],"interuppted":false},{"index":8,"isIgnoredIfFailed":false,"type":"TEST_STEP","name":"click","message":"Object: \u0027Object Repository/MainPage/input_search\u0027 is clicked on","description":"","startTime":1525665964080,"endTime":1525665964266,"childRecords":[{"testStatus":{"stackTrace":"","statusValue":"PASSED"},"type":"MESSAGE","name":"","message":"Object: \u0027Object Repository/MainPage/input_search\u0027 is clicked on","startTime":1525665964266,"endTime":0,"childRecords":[],"interuppted":false}],"interuppted":false},{"index":9,"isIgnoredIfFailed":false,"type":"TEST_STEP","name":"click","message":"Object: \u0027Object Repository/MainPage/a_Home\u0027 is clicked on","description":"","startTime":1525665964267,"endTime":1525665965329,"childRecords":[{"testStatus":{"stackTrace":"","statusValue":"PASSED"},"type":"MESSAGE","name":"","message":"Object: \u0027Object Repository/MainPage/a_Home\u0027 is clicked on","startTime":1525665965329,"endTime":0,"childRecords":[],"interuppted":false}],"interuppted":false},{"index":10,"isIgnoredIfFailed":false,"type":"TEST_STEP","name":"waitForPageLoad","message":"Wait for page load successfully","description":"","startTime":1525665965330,"endTime":1525665965390,"childRecords":[{"testStatus":{"stackTrace":"","statusValue":"PASSED"},"type":"MESSAGE","name":"","message":"Wait for page load successfully","startTime":1525665965390,"endTime":0,"childRecords":[],"interuppted":false}],"interuppted":false},{"index":11,"isIgnoredIfFailed":false,"type":"TEST_STEP","name":"click","message":"Object: \u0027Object Repository/MainPage/a_Organizations\u0027 is clicked on","description":"","startTime":1525665965391,"endTime":1525665966837,"childRecords":[{"testStatus":{"stackTrace":"","statusValue":"PASSED"},"type":"MESSAGE","name":"","message":"Object: \u0027Object Repository/MainPage/a_Organizations\u0027 is clicked on","startTime":1525665966836,"endTime":0,"childRecords":[],"interuppted":false}],"interuppted":false},{"index":12,"isIgnoredIfFailed":false,"type":"TEST_STEP","name":"click","message":"Object: \u0027Object Repository/MainPage/input_Save\u0027 is clicked on","description":"","startTime":1525665966837,"endTime":1525665967574,"childRecords":[{"testStatus":{"stackTrace":"","statusValue":"PASSED"},"type":"MESSAGE","name":"","message":"Object: \u0027Object Repository/MainPage/input_Save\u0027 is clicked on","startTime":1525665967573,"endTime":0,"childRecords":[],"interuppted":false}],"interuppted":false},{"index":13,"isIgnoredIfFailed":false,"type":"TEST_STEP","name":"click","message":"Object: \u0027Object Repository/MainPage/a_Home\u0027 is clicked on","description":"","startTime":1525665967574,"endTime":1525665968586,"childRecords":[{"testStatus":{"stackTrace":"","statusValue":"PASSED"},"type":"MESSAGE","name":"","message":"Object: \u0027Object Repository/MainPage/a_Home\u0027 is clicked on","startTime":1525665968585,"endTime":0,"childRecords":[],"interuppted":false}],"interuppted":false},{"index":14,"isIgnoredIfFailed":false,"type":"TEST_STEP","name":"click","message":"Object: \u0027Object Repository/MainPage/a_Import Application\u0027 is clicked on","description":"","startTime":1525665968587,"endTime":1525665968984,"childRecords":[{"testStatus":{"stackTrace":"","statusValue":"PASSED"},"type":"MESSAGE","name":"","message":"Object: \u0027Object Repository/MainPage/a_Import Application\u0027 is clicked on","startTime":1525665968983,"endTime":0,"childRecords":[],"interuppted":false}],"interuppted":false},{"index":15,"isIgnoredIfFailed":false,"type":"TEST_STEP","name":"click","message":"Object: \u0027Object Repository/MainPage/input_upload\u0027 is clicked on","description":"","startTime":1525665968984,"endTime":1525665969496,"childRecords":[{"testStatus":{"stackTrace":"","statusValue":"PASSED"},"type":"MESSAGE","name":"","message":"Object: \u0027Object Repository/MainPage/input_upload\u0027 is clicked on","startTime":1525665969494,"endTime":0,"childRecords":[],"interuppted":false}],"interuppted":false},{"index":16,"isIgnoredIfFailed":false,"type":"TEST_STEP","name":"click","message":"Object: \u0027Object Repository/MainPage/a_Home\u0027 is clicked on","description":"","startTime":1525665969497,"endTime":1525665970490,"childRecords":[{"testStatus":{"stackTrace":"","statusValue":"PASSED"},"type":"MESSAGE","name":"","message":"Object: \u0027Object Repository/MainPage/a_Home\u0027 is clicked on","startTime":1525665970489,"endTime":0,"childRecords":[],"interuppted":false}],"interuppted":false},{"index":17,"isIgnoredIfFailed":false,"type":"TEST_STEP","name":"click","message":"Object: \u0027Object Repository/MainPage/a_Import Form\u0027 is clicked on","description":"","startTime":1525665970490,"endTime":1525665970905,"childRecords":[{"testStatus":{"stackTrace":"","statusValue":"PASSED"},"type":"MESSAGE","name":"","message":"Object: \u0027Object Repository/MainPage/a_Import Form\u0027 is clicked on","startTime":1525665970905,"endTime":0,"childRecords":[],"interuppted":false}],"interuppted":false},{"index":18,"isIgnoredIfFailed":false,"type":"TEST_STEP","name":"click","message":"Object: \u0027Object Repository/MainPage/form_Form Version Archive File\u0027 is clicked on","description":"","startTime":1525665970905,"endTime":1525665970984,"childRecords":[{"testStatus":{"stackTrace":"","statusValue":"PASSED"},"type":"MESSAGE","name":"","message":"Object: \u0027Object Repository/MainPage/form_Form Version Archive File\u0027 is clicked on","startTime":1525665970984,"endTime":0,"childRecords":[],"interuppted":false}],"interuppted":false},{"index":19,"isIgnoredIfFailed":false,"type":"TEST_STEP","name":"click","message":"Object: \u0027Object Repository/MainPage/input_upload\u0027 is clicked on","description":"","startTime":1525665970984,"endTime":1525665971376,"childRecords":[{"testStatus":{"stackTrace":"","statusValue":"PASSED"},"type":"MESSAGE","name":"","message":"Object: \u0027Object Repository/MainPage/input_upload\u0027 is clicked on","startTime":1525665971375,"endTime":0,"childRecords":[],"interuppted":false}],"interuppted":false},{"index":20,"isIgnoredIfFailed":false,"type":"TEST_STEP","name":"click","message":"Object: \u0027Object Repository/MainPage/a_Home\u0027 is clicked on","description":"","startTime":1525665971376,"endTime":1525665973646,"childRecords":[{"testStatus":{"stackTrace":"","statusValue":"PASSED"},"type":"MESSAGE","name":"","message":"Object: \u0027Object Repository/MainPage/a_Home\u0027 is clicked on","startTime":1525665973645,"endTime":0,"childRecords":[],"interuppted":false}],"interuppted":false},{"index":21,"isIgnoredIfFailed":false,"type":"TEST_STEP","name":"click","message":"Object: \u0027Object Repository/MainPage/a_Logout\u0027 is clicked on","description":"","startTime":1525665973646,"endTime":1525665974375,"childRecords":[{"testStatus":{"stackTrace":"","statusValue":"PASSED"},"type":"MESSAGE","name":"","message":"Object: \u0027Object Repository/MainPage/a_Logout\u0027 is clicked on","startTime":1525665974374,"endTime":0,"childRecords":[],"interuppted":false}],"interuppted":false},{"index":22,"isIgnoredIfFailed":false,"type":"TEST_STEP","name":"closeBrowser","message":"Browser is closed","description":"","startTime":1525665974375,"endTime":1525665975048,"childRecords":[{"testStatus":{"stackTrace":"","statusValue":"PASSED"},"type":"MESSAGE","name":"","message":"Browser is closed","startTime":1525665975047,"endTime":0,"childRecords":[],"interuppted":false}],"interuppted":false},{"testStatus":{"stackTrace":"","statusValue":"PASSED"},"type":"MESSAGE","name":"","message":"Test Cases/Testcase1","startTime":1525665975048,"endTime":0,"childRecords":[],"interuppted":false}],"interuppted":false},{"isOptional":false,"type":"TEST_CASE","name":"Test Cases/Testcase2","id":"Test Cases/Testcase2","source":"C:\\\\Users\\\\smanugunta\\\\git\\\\Test\\\\Test Cases\\\\Testcase2.tc","message":"Test Cases/Testcase2","description":"","startTime":1525665977102,"endTime":1525665999731,"childRecords":[{"testStatus":{"stackTrace":"","statusValue":"INFO"},"type":"MESSAGE","name":"","message":"Evaluating variables for test case","startTime":1525665977117,"endTime":0,"childRecords":[],"interuppted":false},{"index":1,"isIgnoredIfFailed":false,"type":"TEST_STEP","name":"openBrowser","message":"Browser is opened with url: \u0027\u0027","description":"","startTime":1525665977228,"endTime":1525665979281,"childRecords":[{"testStatus":{"stackTrace":"","statusValue":"PASSED"},"type":"MESSAGE","name":"","message":"Browser is opened with url: \u0027\u0027","startTime":1525665979281,"endTime":0,"childRecords":[],"interuppted":false}],"interuppted":false},{"index":2,"isIgnoredIfFailed":false,"type":"TEST_STEP","name":"navigateToUrl","message":"Navigate to \u0027https://tm.test1.avoka.com/manager/login.htm\u0027 successfully","description":"","startTime":1525665979281,"endTime":1525665981231,"childRecords":[{"testStatus":{"stackTrace":"","statusValue":"PASSED"},"type":"MESSAGE","name":"","message":"Navigate to \u0027https://tm.test1.avoka.com/manager/login.htm\u0027 successfully","startTime":1525665981230,"endTime":0,"childRecords":[],"interuppted":false}],"interuppted":false},{"index":3,"isIgnoredIfFailed":false,"type":"TEST_STEP","name":"setText","message":"Text \u0027smanugunta@avoka.com\u0027 is set on object \u0027Object Repository/Page_Manager - Avoka Transact/input_j_username\u0027","description":"","startTime":1525665981231,"endTime":1525665981503,"childRecords":[{"testStatus":{"stackTrace":"","statusValue":"PASSED"},"type":"MESSAGE","name":"","message":"Text \u0027smanugunta@avoka.com\u0027 is set on object \u0027Object Repository/Page_Manager - Avoka Transact/input_j_username\u0027","startTime":1525665981503,"endTime":0,"childRecords":[],"interuppted":false}],"interuppted":false},{"index":4,"isIgnoredIfFailed":false,"type":"TEST_STEP","name":"setText","message":"Text \u0027Unicorn!23\u0027 is set on object \u0027Object Repository/Page_Manager - Avoka Transact/input_j_password\u0027","description":"","startTime":1525665981503,"endTime":1525665981617,"childRecords":[{"testStatus":{"stackTrace":"","statusValue":"PASSED"},"type":"MESSAGE","name":"","message":"Text \u0027Unicorn!23\u0027 is set on object \u0027Object Repository/Page_Manager - Avoka Transact/input_j_password\u0027","startTime":1525665981616,"endTime":0,"childRecords":[],"interuppted":false}],"interuppted":false},{"index":5,"isIgnoredIfFailed":false,"type":"TEST_STEP","name":"click","message":"Object: \u0027Object Repository/Page_Manager - Avoka Transact/input_btn btn-primary\u0027 is clicked on","description":"","startTime":1525665981617,"endTime":1525665987821,"childRecords":[{"testStatus":{"stackTrace":"","statusValue":"PASSED"},"type":"MESSAGE","name":"","message":"Object: \u0027Object Repository/Page_Manager - Avoka Transact/input_btn btn-primary\u0027 is clicked on","startTime":1525665987821,"endTime":0,"childRecords":[],"interuppted":false}],"interuppted":false},{"index":6,"isIgnoredIfFailed":false,"type":"TEST_STEP","name":"click","message":"Object: \u0027Object Repository/Page_Manager - Avoka Transact/a_Forms2\u0027 is clicked on","description":"","startTime":1525665987822,"endTime":1525665987925,"childRecords":[{"testStatus":{"stackTrace":"","statusValue":"PASSED"},"type":"MESSAGE","name":"","message":"Object: \u0027Object Repository/Page_Manager - Avoka Transact/a_Forms2\u0027 is clicked on","startTime":1525665987925,"endTime":0,"childRecords":[],"interuppted":false}],"interuppted":false},{"index":7,"isIgnoredIfFailed":false,"type":"TEST_STEP","name":"navigateToUrl","message":"Navigate to \u0027https://tm.test1.avoka.com/manager/admin/form/form-search.htm?_wid\u003d15\u0027 successfully","description":"","startTime":1525665987925,"endTime":1525665990106,"childRecords":[{"testStatus":{"stackTrace":"","statusValue":"PASSED"},"type":"MESSAGE","name":"","message":"Navigate to \u0027https://tm.test1.avoka.com/manager/admin/form/form-search.htm?_wid\u003d15\u0027 successfully","startTime":1525665990105,"endTime":0,"childRecords":[],"interuppted":false}],"interuppted":false},{"index":8,"isIgnoredIfFailed":false,"type":"TEST_STEP","name":"click","message":"Object: \u0027Object Repository/Page_Manager - Avoka Transact/Navigate\u0027 is clicked on","description":"","startTime":1525665990107,"endTime":1525665990233,"childRecords":[{"testStatus":{"stackTrace":"","statusValue":"PASSED"},"type":"MESSAGE","name":"","message":"Object: \u0027Object Repository/Page_Manager - Avoka Transact/Navigate\u0027 is clicked on","startTime":1525665990233,"endTime":0,"childRecords":[],"interuppted":false}],"interuppted":false},{"index":9,"isIgnoredIfFailed":false,"type":"TEST_STEP","name":"switchToWindowTitle","message":"Switched to window with title: \u002718.04 for Stuart\u0027","description":"","startTime":1525665990233,"endTime":1525665994821,"childRecords":[{"testStatus":{"stackTrace":"","statusValue":"PASSED"},"type":"MESSAGE","name":"","message":"Switched to window with title: \u002718.04 for Stuart\u0027","startTime":1525665994821,"endTime":0,"childRecords":[],"interuppted":false}],"interuppted":false},{"index":10,"isIgnoredIfFailed":false,"type":"TEST_STEP","name":"click","message":"Object: \u0027Object Repository/Page_18.04 for Stuart/span_Continue\u0027 is clicked on","description":"","startTime":1525665994821,"endTime":1525665995022,"childRecords":[{"testStatus":{"stackTrace":"","statusValue":"PASSED"},"type":"MESSAGE","name":"","message":"Object: \u0027Object Repository/Page_18.04 for Stuart/span_Continue\u0027 is clicked on","startTime":1525665995021,"endTime":0,"childRecords":[],"interuppted":false}],"interuppted":false},{"index":11,"isIgnoredIfFailed":false,"type":"TEST_STEP","name":"click","message":"Object: \u0027Object Repository/Page_18.04 for Stuart/span_Submit\u0027 is clicked on","description":"","startTime":1525665995022,"endTime":1525665995166,"childRecords":[{"testStatus":{"stackTrace":"","statusValue":"PASSED"},"type":"MESSAGE","name":"","message":"Object: \u0027Object Repository/Page_18.04 for Stuart/span_Submit\u0027 is clicked on","startTime":1525665995166,"endTime":0,"childRecords":[],"interuppted":false}],"interuppted":false},{"index":12,"isIgnoredIfFailed":false,"type":"TEST_STEP","name":"switchToWindowTitle","message":"Switched to window with title: \u0027Manager - Avoka Transact\u0027","description":"","startTime":1525665995167,"endTime":1525665995211,"childRecords":[{"testStatus":{"stackTrace":"","statusValue":"PASSED"},"type":"MESSAGE","name":"","message":"Switched to window with title: \u0027Manager - Avoka Transact\u0027","startTime":1525665995210,"endTime":0,"childRecords":[],"interuppted":false}],"interuppted":false},{"index":13,"isIgnoredIfFailed":false,"type":"TEST_STEP","name":"click","message":"Object: \u0027Object Repository/Page_Manager - Avoka Transact/a_Operations\u0027 is clicked on","description":"","startTime":1525665995212,"endTime":1525665995321,"childRecords":[{"testStatus":{"stackTrace":"","statusValue":"PASSED"},"type":"MESSAGE","name":"","message":"Object: \u0027Object Repository/Page_Manager - Avoka Transact/a_Operations\u0027 is clicked on","startTime":1525665995321,"endTime":0,"childRecords":[],"interuppted":false}],"interuppted":false},{"index":14,"isIgnoredIfFailed":false,"type":"TEST_STEP","name":"navigateToUrl","message":"Navigate to \u0027https://tm.test1.avoka.com/manager/admin/submission/submission-search.htm?_wid\u003d31\u0027 successfully","description":"","startTime":1525665995321,"endTime":1525665996238,"childRecords":[{"testStatus":{"stackTrace":"","statusValue":"PASSED"},"type":"MESSAGE","name":"","message":"Navigate to \u0027https://tm.test1.avoka.com/manager/admin/submission/submission-search.htm?_wid\u003d31\u0027 successfully","startTime":1525665996237,"endTime":0,"childRecords":[],"interuppted":false}],"interuppted":false},{"index":15,"isIgnoredIfFailed":false,"type":"TEST_STEP","name":"click","message":"Object: \u0027Object Repository/Page_Manager - Avoka Transact/a_Logout\u0027 is clicked on","description":"","startTime":1525665996239,"endTime":1525665996988,"childRecords":[{"testStatus":{"stackTrace":"","statusValue":"PASSED"},"type":"MESSAGE","name":"","message":"Object: \u0027Object Repository/Page_Manager - Avoka Transact/a_Logout\u0027 is clicked on","startTime":1525665996988,"endTime":0,"childRecords":[],"interuppted":false}],"interuppted":false},{"index":16,"isIgnoredIfFailed":false,"type":"TEST_STEP","name":"closeBrowser","message":"Browser is closed","description":"","startTime":1525665996989,"endTime":1525665997638,"childRecords":[{"testStatus":{"stackTrace":"","statusValue":"PASSED"},"type":"MESSAGE","name":"","message":"Browser is closed","startTime":1525665997638,"endTime":0,"childRecords":[],"interuppted":false}],"interuppted":false},{"testStatus":{"stackTrace":"","statusValue":"PASSED"},"type":"MESSAGE","name":"","message":"Test Cases/Testcase2","startTime":1525665997638,"endTime":0,"childRecords":[],"interuppted":false}],"interuppted":false}],"interuppted":false}